git_permalink_fixer/__init__.py
git_permalink_fixer/__main__.py
git_permalink_fixer/app.py
git_permalink_fixer/constants.py
git_permalink_fixer/examination_set.py
git_permalink_fixer/file_ops.py
git_permalink_fixer/git_utils.py
git_permalink_fixer/global_prefs.py
git_permalink_fixer/operation_set.py
git_permalink_fixer/permalink_info.py
git_permalink_fixer/session_prefs.py
git_permalink_fixer/text_utils.py
git_permalink_fixer/url_utils.py
git_permalink_fixer/web_utils.py
git_permalink_fixer-0.2.0.dist-info/METADATA
git_permalink_fixer-0.2.0.dist-info/WHEEL
git_permalink_fixer-0.2.0.dist-info/entry_points.txt
git_permalink_fixer-0.2.0.dist-info/licenses/LICENSE
git_permalink_fixer-0.2.0.dist-info/RECORD
