Metadata-Version: 2.4
Name: git-permalink-fixer
Version: 0.2.0
Summary: A tool to find, replace, and protect GitHub permalinks in your project.
Project-URL: Homepage, https://github.com/huyz/git-permalink-fixer
Project-URL: Bug Tracker, https://github.com/huyz/git-permalink-fixer/issues
Project-URL: Repository, https://github.com/huyz/git-permalink-fixer
Author-email: huyz <huyz@users.noreply.github.com>
License: MIT License
License-File: LICENSE
Keywords: git,git-tag,github,permalink
Classifier: Development Status :: 4 - Beta
Classifier: Environment :: Console
Classifier: Intended Audience :: Developers
Classifier: License :: OSI Approved :: MIT License
Classifier: Operating System :: OS Independent
Classifier: Programming Language :: Python :: 3
Classifier: Programming Language :: Python :: 3.9
Classifier: Programming Language :: Python :: 3.10
Classifier: Programming Language :: Python :: 3.11
Classifier: Programming Language :: Python :: 3.12
Classifier: Programming Language :: Python :: Implementation :: CPython
Classifier: Programming Language :: Python :: Implementation :: PyPy
Classifier: Topic :: Software Development :: Version Control :: Git
Classifier: Topic :: Utilities
Requires-Python: >=3.9
Requires-Dist: requests>=2.32.3
